Workbook

Sheet 自学 （6级）
A2: 1 | B2: 过滤 | C2: Guòlǜ | D2: To filter, Filterate | F2: 这水得先过滤一下才能喝。 | G2: 你把那些没用的信息过滤掉吧。
A3: 2 | B3: 争夺 | C3: zhēngduó | D3: To fight for | F3: 两家公司在争夺同一个客户。 | G3: 他为了那个职位跟别人争夺了好几个月。
A4: 3 | B4: 将近 | C4: jiāngjìn | D4: Approximately | F4: 我在这里住了将近十年了。 | G4: 我们的目标完成率将近百分之九十。
A5: 4 | B5: 进而 | C5: jìn'ér | D5: And then | F5: 他先学了中文，进而开始研究中国文化。 | G5: 我希望先了解，再进而改进方法。
A6: 5 | B6: 况且 | C6: kuàngqiě | D6: Moreover, in addition | F6: 我今天太累了，况且明天还要早起。 | G6: 他不会去的，况且天气也不好。
A7: 6 | B7: 宁肯 | C7: nìngkěn | D7: Would rather | F7: 我宁肯多花点时间，也不想做错。 | G7: 他宁肯自己受累，也不愿麻烦别人。
A8: 7 | B8: 颇 | C8: pō | D8: Quite | F8: 他对这个问题颇有研究。 | G8: 这道菜味道颇不错。
A9: 8 | B9: 拣 | C9: jiǎn | D9: Pick up | F9: 我拣了几瓶矿泉水回来。 | G9: 你拣个颜色好看的吧。
A10: 9 | B10: 维持 | C10: wéichí | D10: To preserve, to maintain | F10: 我们得努力维持现在的生活水平。 | G10: 他们之间的关系很难维持下去。
A11: 10 | B11: 分裂 | C11: fēnliè | D11: To split, to divide | F11: 团队因为意见不合快要分裂了。 | G11: 家庭的分裂让孩子很难过。
A12: 11 | B12: 跟随 | C12: Gēnsuí | D12: Follow | F12: 我打算跟随师傅学一年。 | G12: 我打算跟随师傅学一年。
A13: 12 | B13: 寻觅 | C13: xúnmì | D13: To look for, seek for | F13: 我在城市里寻觅那家老餐馆。 | G13: 她一直在寻觅理想的工作。
... A148: 147 | B148: 决策 | C148: juécè | D148: to make a strategic decision | F148: 公司高层正在讨论新的发展决策。 | G148: 领导层经过反复讨论，最终作出了关键的战略决策。
A149: 148 | B149: 土壤 | C149: Tǔrǎng | D149: Soil | E149: 土壤不是很肥沃。
A150: 149 | B150: 陡峭 | C150: dǒuqiào | D150: Steep, Precipious | E150: 丝瓜已经爬上了我们大楼陡峭的楼墙。
A151: 150 | B151: 茂盛 | C151: màoshèng | D151: Luxuriant, exuberant | E151: 叶子茂盛
A152: 151 | B152: 悬挂 | C152: xuánguà | D152: to hang, to suspend | E152: 她悬挂在空中
A153: 152 | B153: 负担 | C153: fùdān | D153: to bear, to shoulder | E153: 丝瓜茎好像负担不起抓的重量。
A154: 153 | B154: 坠 | C154: zhuì | D154: to fall, to drop | E154: 时刻都要坠落下来
A155: 154 | B155: 吊 | C155: diào | D155: to hang, to suspend, to dangle | E155: 垂直地吊在那里
A156: 155 | B156: 点缀 | C156: diǎnzhuì | D156: to decorate, to adorn | E156: 黄色的花瓣点缀在绿叶之间。
A157: 156 | B157: 协调 | C157: xiétiáo | D157: coordinated, harmonious | E157: 颜色协调
A158: 157 | B158: 连同 | C158: liántóng | D158: together with, along with | E158: 连同上面的两个大丝瓜一起坠落到地下。
A159: 158 | B159: 断定 | C159: duàndìng | D159: to form judgement, to conclude | E159: 我断定的说
A160: 159 | B160: 晃 | C160: huǎng | D160: to shake, to sway | E160: 在风中晃来晃去
... A179: 178 | B179: 跳跃 | C179: tiàoyuè | D179: to jump, to leap | E179: 猫为什么能快速跳跃起来
A180: 179 | B180: 间隔 | C180: jiàngé | D180: interval, intermission
A181: 180 | B181: 姑且 | C181: gūqiě | D181: fo the moment, tentatively | E181: 他们姑且换一个文雅的称呼吧
A182: 181 | B182: 笨拙 | C182: bènzhuō | D182: clumsy, stupid | E182: 笨拙的大象
A183: 182 | B183: 闪烁 | C183: shǎnshuò | D183: to twinkle, to flicker, to glitter | E183: 他们看到的是一明一暗的闪烁
A184: 183 | B184: 实力 | C184: shílì | D184: vision, eyesight | E184: 我们的实力看到的就会是一个连续的光
A185: 184 | B185: 文雅 | C185: wényǎ | D185: elegant, refined, polished | E185: 他们姑且换一个文雅的称呼吧
A186: 185 | B186: 新陈代谢 （代谢） | C186: xīnchéndàixiè (dàixiè) | D186: metabolism | E186: 新陈代谢速率有效
A187: 186 | B187: 名次 | C187: míngcì | D187: ranking, place in a competition
A188: 187 | B188: 推论 | C188: tuīlùn | D188: to infer, to deduce
A189: 188 | B189: 实惠 | C189: shíhuì | D189: practical, affordable, substantial
A190: 189 | B190: 渺小 | C190: miǎoxiǎo | D190: tiny, insgnificant
A191: 190 | B191: 焦急 | C191: jiāojí | D191: anxious, agitated
A192: 191 | B192: 系列 | C192: xìliè | D192: series, set
A193: 192 | B193: 深奥 | C193: shēn'ào | D193: deep, abstruse
A194: 193 | B194: 标记 | C194: biāojì | D194: to mark, to label
A195: 194 | B195: 论证 | C195: lùnzhèng | D195: to expound and prove
A196: 195 | B196: 苍蝇 | C196: cāngyíng | D196: fly
A197: 196 | B197: 完毕 | C197: Wánbì | D197: to finish
A198: 197 | B198: 注视 | C198: zhùshì | D198: to gare at, to look attentively at
... A455: 454 | B455: 继承 | C455: jìchéng | D455: to inherent
A456: 455 | B456: 奴隶 | D456: slave
A457: 456 | B457: 粥 | D457: porriage, gruel
A458: 457 | B458: 往常 | D458: usually, habitually in the past
A459: 458 | B459: 侦探 | D459: detective
A460: 459 | B460: 特长 | D460: one's strong suit, forte
A461: 460 | B461: 摇滚 | D461: rock and roll
A462: 461 | B462: 憋 | D462: to surpress, to hold back
A463: 462 | B463: 绑架 | D463: to kidnap
A464: 463 | B464: 受罪 | D464: to suffer hardship
A465: 464 | B465: 吼 | D465: to shout, to roar
A466: 465 | B466: 伺候 | D466: to serve, to wait upon
A467: 466 | B467: 眨 | D467: to blink, to wink
... A485: 484 | B485: 干扰 | D485: to disburb, to interfere
A486: 485

Sheet Sheet1
A1: Column1 | B1: Column2 | C1: Column3 | D1: Column4 | F1: 巴不得 – eagerly wish, can't wait for
A2: 一向 | D2: 巴不得 | F2: 我巴不得明天就能见到你。 / I can’t wait to see you tomorrow.
A3: 一度 | D3: 别提多。。。了
A4: 不妨 | D4: 恨不得 | F4: 别提多。。。了 – extremely, you can’t imagine how…
A5: 不得已 | D5: 顿时 | F5: 这道菜好吃得别提多了！ / This dish is incredibly delicious!
A6: 不料 | D6: 不由得
A7: 不禁 | D7: 番 | F7: 恨不得 – wish one could, eager to
A8: 不顾 | D8: 过于 | F8: 我恨不得立刻搬到海边去住。 / I wish I could move to the seaside immediately.
A9: 仍旧 | D9: 着呢
A10: 令人 | D10: 乘机 | F10: 顿时 – instantly, at once
A11: 以便 | D11: 不料 | F11: 听到这个消息，他顿时愣住了。 / Hearing the news, he was instantly stunned.
A12: 以致 | D12: 未免
A13: 例外 | D13: 而已 | F13: 不由得 – can’t help but
A14: 依旧 | D14: 固然 | F14: 看到孩子们玩耍，我不由得笑了。 / Seeing the children playing, I couldn’t help but laugh.
A15: 便于 | D15: 无非
A16: 便于 | D16: 唯独 | F16: 番 – (measure word for efforts or times)
A17: 倘若 | D17: 明明 | F17: 他又试了一番，终于成功了。 / He tried again and finally succeeded.
A18: 免得 | D18: 大不了
A19: 况且 | D19: 于 | F19: 过于 – excessively
A20: 创立 | D20: 致使 | F20: 你过于担心没必要。 / You are worrying excessively, which is unnecessary.
A21: 刹那 | D21: 并非
A22: 务必 | D22: 对。。。而言 | F22: 着呢 – emphasizing a state (colloquial)
A23: 勉强 | D23: 有关 | F23: 他忙着呢，别打扰他。 / He’s busy, don’t disturb him.
A24: 即时 | D24: 不瞒你说
A25: 历来 | D25: 以至 | F25: 乘机 – take advantage of an opportunity
A26: 及早 | D26: 即便 | F26: 他乘机解释了自己的观点。 / He took the opportunity to explain his point of view.
A27: 固然 | D27: 所在
A28: 大不了 | D28: 统统 | F28: 不料 – unexpectedly
A29: 姑且 | D29: 该干吗干吗 | F29: 不料今天竟然下起了大雨。 / Unexpectedly, it rained heavily today.
A30: 宁肯 | D30: 不妨
A31: 将就 | D31: 务必 | F31: 未免 – rather, a bit too
A32: 将近 | D32: 鉴于 | F32: 他说话未免太直接了。 / He speaks rather too directly.
A33: 巴不得 | D33: 便于
A34: 并非 | D34: 犹如 | F34: 而已 – only, that’s all
A35: 当初 | D35: 和。。。相比 | F35: 我只是随便看看而已。 / I’m just casually looking, that’s all.
A36: 忍受 | D36: 难以
A37: 恰巧 | D37: 免得 | F37: 固然 – admittedly, it is true
A38: 无非 | D38: 时而 | F38: 固然他很忙，但还是抽时间来看我。 / Admittedly, he is busy, but he still took time to visit me.
A39: 时而 | D39: 不禁
A40: 未免 | D40: 无不 | F40: 无非 – nothing but
A41: 极端 | D41: 足以 | F41: 他无非是想帮忙而已。 / He is nothing but trying to help.
A42: 毫无 | D42: 为。。。所。。
A43: 涉及 | D43: 姑且 | F43: 唯独 – only, alone
A44: 爽快 | D44: 随即 | F44: 唯独你忘了带钥匙。 / Only you forgot to bring the key.
A45: 片刻 | D45: 宁愿
A46: 犹如 | D46: 进而 | F46: 明明 – obviously, clearly
A47: 瞬间 | D47: 得以 | F47: 明明是他错了，他却不承认。 / Clearly he was wrong, but he didn’t admit it.
A48: 穿越 | D48: 偏偏
A49: 统统 | D49: 况且 | F49: 大不了 – at most, at the worst
A50: 致使 | D50: 倒不如 | F50: 大不了我重新开始一次。 / At worst, I’ll start over.
A51: 若干 | D51: 起码
A52: 触犯 | D52: 至少 | F52: 于 – regarding, in relation to
A53: 譬如 | D53: 日益 | F53: 这个问题于我来说很重要。 / This issue is very important to me.
A54: 起初 | D54: 凡是
A55: 足以 | D55: 所有 | F55: 致使 – to cause, to lead to
A56: 过于 | D56: 急切 | F56: 他的迟到致使会议延迟开始。 / His being late caused the meeting to start late.
A57: 近来 | D57: 急忙
A58: 进而 | D58: 不得已 | F58: 并非 – not to be, not
A59: 鉴于 | D59: 不得不 | F59: 事实并非如此。 / The fact is not like that.
A60: 顿时 | D60: 一向
A61: 颇 | D61: 一度 | F61: 对。。。而言 – as far as … is concerned
D62: 拥有 | F62: 对我而言，健康最重要。 / As far as I’m concerned, health is the most important.
D63: 具有
D64: 以便 | F64: 有关 – related to
D65: 便于 | F65: 这本书有关中国历史。 / This book is related to Chinese history.
D66: 势必
D67: 一定 | F67: 不瞒你说 – to be honest, frankly
D68: 历来 | F68: 不瞒你说，我不太喜欢这部电影。 / To be honest, I don’t like this movie much.
D69: 从来
D70: 连同 | F70: 以至 – so much that, to the extent that
D71: 一起 | F71: 他工作太忙，以至于没时间休息。 / He is so busy with work that he has no time to rest.
D72: 将近
D73: 将要 | F73: 即便 – even if
D74: 将就 | F74: 即便下雨，我也要去跑步。 / Even if it rains, I will go running.
F76: 所在 – place, location
F77: 我常去的所在是图书馆。 / The place I often go to is the library.
F79: 统统 – all, completely
F80: 这些文件统统都需要签字。 / All of these documents need to be signed.
F82: 该干吗干吗 – do whatever one should do
F83: 你该干吗干吗，我不管。 / Do whatever you should do, I won’t interfere.
F85: 不妨 – there is no harm in
F86: 你不妨试一试这个方法。 / You might as well try this method.
F88: 务必 – must, to be sure to
F89: 开会前务必准备好资料。 / Be sure to prepare the materials before the meeting.
F91: 鉴于 – in view of
F92: 鉴于天气不好，活动取消了。 / In view of the bad weather, the event was canceled.
... F215: 这个房间不大，但我们将就住吧。 / The room is small, but we’ll make do with it.

Sheet Test
C1: Result | D1: Answer | F1: =H15 -> 158 | K1: =H16 -> 36
A2: ='自学 （6级）'!D2 -> To filter, Filterate | C2: =IF(OR(ISBLANK(B2),'自学 （6级）'!B2=""),"UNANSWERED", IF('自学 （6级）'!B2=B2,"TRUE","FALSE")) -> UNANSWERED | D2: =IF(OR(ISBLANK(B2),ISBLANK('自学 （6级）'!B2)),"", IF(B2='自学 （6级）'!B2,"",'自学 （6级）'!B2))
A3: ='自学 （6级）'!D3 -> To fight for | C3: =IF(OR(ISBLANK(B3),'自学 （6级）'!B3=""),"UNANSWERED", IF('自学 （6级）'!B3=B3,"TRUE","FALSE")) -> UNANSWERED | D3: =IF(OR(ISBLANK(B3),ISBLANK('自学 （6级）'!B3)),"", IF(B3='自学 （6级）'!B3,"",'自学 （6级）'!B3))
A4: ='自学 （6级）'!D4 -> Approximately | C4: =IF(OR(ISBLANK(B4),'自学 （6级）'!B4=""),"UNANSWERED", IF('自学 （6级）'!B4=B4,"TRUE","FALSE")) -> UNANSWERED | D4: =IF(OR(ISBLANK(B4),ISBLANK('自学 （6级）'!B4)),"", IF(B4='自学 （6级）'!B4,"",'自学 （6级）'!B4))
A5: ='自学 （6级）'!D5 -> And then | C5: =IF(OR(ISBLANK(B5),'自学 （6级）'!B5=""),"UNANSWERED", IF('自学 （6级）'!B5=B5,"TRUE","FALSE")) -> UNANSWERED | D5: =IF(OR(ISBLANK(B5),ISBLANK('自学 （6级）'!B5)),"", IF(B5='自学 （6级）'!B5,"",'自学 （6级）'!B5))
A6: ='自学 （6级）'!D6 -> Moreover, in addition | C6: =IF(OR(ISBLANK(B6),'自学 （6级）'!B6=""),"UNANSWERED", IF('自学 （6级）'!B6=B6,"TRUE","FALSE")) -> UNANSWERED | D6: =IF(OR(ISBLANK(B6),ISBLANK('自学 （6级）'!B6)),"", IF(B6='自学 （6级）'!B6,"",'自学 （6级）'!B6))
A7: ='自学 （6级）'!D7 -> Would rather | C7: =IF(OR(ISBLANK(B7),'自学 （6级）'!B7=""),"UNANSWERED", IF('自学 （6级）'!B7=B7,"TRUE","FALSE")) -> UNANSWERED | D7: =IF(OR(ISBLANK(B7),ISBLANK('自学 （6级）'!B7)),"", IF(B7='自学 （6级）'!B7,"",'自学 （6级）'!B7))
A8: ='自学 （6级）'!D8 -> Quite | C8: =IF(OR(ISBLANK(B8),'自学 （6级）'!B8=""),"UNANSWERED", IF('自学 （6级）'!B8=B8,"TRUE","FALSE")) -> UNANSWERED | D8: =IF(OR(ISBLANK(B8),ISBLANK('自学 （6级）'!B8)),"", IF(B8='自学 （6级）'!B8,"",'自学 （6级）'!B8))
A9: ='自学 （6级）'!D9 -> Pick up | C9: =IF(OR(ISBLANK(B9),'自学 （6级）'!B9=""),"UNANSWERED", IF('自学 （6级）'!B9=B9,"TRUE","FALSE")) -> UNANSWERED | D9: =IF(OR(ISBLANK(B9),ISBLANK('自学 （6级）'!B9)),"", IF(B9='自学 （6级）'!B9,"",'自学 （6级）'!B9))
A10: ='自学 （6级）'!D10 -> To preserve, to maintain | C10: =IF(OR(ISBLANK(B10),'自学 （6级）'!B10=""),"UNANSWERED", IF('自学 （6级）'!B10=B10,"TRUE","FALSE")) -> UNANSWERED | D10: =IF(OR(ISBLANK(B10),ISBLANK('自学 （6级）'!B10)),"", IF(B10='自学 （6级）'!B10,"",'自学 （6级）'!B10)) | F10: =(F1/312) -> 0.50641026
A11: ='自学 （6级）'!D11 -> To split, to divide | C11: =IF(OR(ISBLANK(B11),'自学 （6级）'!B11=""),"UNANSWERED", IF('自学 （6级）'!B11=B11,"TRUE","FALSE")) -> UNANSWERED | D11: =IF(OR(ISBLANK(B11),ISBLANK('自学 （6级）'!B11)),"", IF(B11='自学 （6级）'!B11,"",'自学 （6级）'!B11))
A12: ='自学 （6级）'!D12 -> Follow | C12: =IF(OR(ISBLANK(B12),'自学 （6级）'!B12=""),"UNANSWERED", IF('自学 （6级）'!B12=B12,"TRUE","FALSE")) -> UNANSWERED | D12: =IF(OR(ISBLANK(B12),ISBLANK('自学 （6级）'!B12)),"", IF(B12='自学 （6级）'!B12,"",'自学 （6级）'!B12))
A13: ='自学 （6级）'!D13 -> To look for, seek for | C13: =IF(OR(ISBLANK(B13),'自学 （6级）'!B13=""),"UNANSWERED", IF('自学 （6级）'!B13=B13,"TRUE","FALSE")) -> UNANSWERED | D13: =IF(OR(ISBLANK(B13),ISBLANK('自学 （6级）'!B13)),"", IF(B13='自学 （6级）'!B13,"",'自学 （6级）'!B13))
A14: ='自学 （6级）'!D14 -> Exaggeration | C14: =IF(OR(ISBLANK(B14),'自学 （6级）'!B14=""),"UNANSWERED", IF('自学 （6级）'!B14=B14,"TRUE","FALSE")) -> UNANSWERED | D14: =IF(OR(ISBLANK(B14),ISBLANK('自学 （6级）'!B14)),"", IF(B14='自学 （6级）'!B14,"",'自学 （6级）'!B14))
A15: ='自学 （6级）'!D15 -> Clearly, plainly | C15: =IF(OR(ISBLANK(B15),'自学 （6级）'!B15=""),"UNANSWERED", IF('自学 （6级）'!B15=B15,"TRUE","FALSE")) -> UNANSWERED | D15: =IF(OR(ISBLANK(B15),ISBLANK('自学 （6级）'!B15)),"", IF(B15='自学 （6级）'!B15,"",'自学 （6级）'!B15)) | G15: Mark | H15: =SUMPRODUCT(--(TRIM(C2:C312)="TRUE")) -> 158 | L15: =F1/COUNTIFS(C2:C312,"UNANSWERED") -> 1.3504274
A16: ='自学 （6级）'!D16 -> Greedy | C16: =IF(OR(ISBLANK(B16),'自学 （6级）'!B16=""),"UNANSWERED", IF('自学 （6级）'!B16=B16,"TRUE","FALSE")) -> UNANSWERED | D16: =IF(OR(ISBLANK(B16),ISBLANK('自学 （6级）'!B16)),"", IF(B16='自学 （6级）'!B16,"",'自学 （6级）'!B16)) | G16: Lose | H16: =SUMPRODUCT(--(TRIM($C$2:$C$312)="FALSE")) -> 36
A17: ='自学 （6级）'!D17 -> All through ages, always | C17: =IF(OR(ISBLANK(B17),'自学 （6级）'!B17=""),"UNANSWERED", IF('自学 （6级）'!B17=B17,"TRUE","FALSE")) -> UNANSWERED | D17: =IF(OR(ISBLANK(B17),ISBLANK('自学 （6级）'!B17)),"", IF(B17='自学 （6级）'!B17,"",'自学 （6级）'!B17)) | G17: Total
A18: ='自学 （6级）'!D18 -> To lose, forfeit | C18: =IF(OR(ISBLANK(B18),'自学 （6级）'!B18=""),"UNANSWERED", IF('自学 （6级）'!B18=B18,"TRUE","FALSE")) -> UNANSWERED | D18: =IF(OR(ISBLANK(B18),ISBLANK('自学 （6级）'!B18)),"", IF(B18='自学 （6级）'!B18,"",'自学 （6级）'!B18))
A19: ='自学 （6级）'!D19 -> Endure | C19: =IF(OR(ISBLANK(B19),'自学 （6级）'!B19=""),"UNANSWERED", IF('自学 （6级）'!B19=B19,"TRUE","FALSE")) -> UNANSWERED | D19: =IF(OR(ISBLANK(B19),ISBLANK('自学 （6级）'!B19)),"", IF(B19='自学 （6级）'!B19,"",'自学 （6级）'!B19)) | G19: Day 1 | H19: Day 2 | I19: Day 3 | J19: Day 4 | K19: Day 5 | L19: Day 6 | M19: Day 7
A20: ='自学 （6级）'!D20 -> Taste, Flavor | C20: =IF(OR(ISBLANK(B20),'自学 （6级）'!B20=""),"UNANSWERED", IF('自学 （6级）'!B20=B20,"TRUE","FALSE")) -> UNANSWERED | D20: =IF(OR(ISBLANK(B20),ISBLANK('自学 （6级）'!B20)),"", IF(B20='自学 （6级）'!B20,"",'自学 （6级）'!B20)) | G20: 诱惑
A21: ='自学 （6级）'!D21 -> To firmly believe | C21: =IF(OR(ISBLANK(B21),'自学 （6级）'!B21=""),"UNANSWERED", IF('自学 （6级）'!B21=B21,"TRUE","FALSE")) -> UNANSWERED | D21: =IF(OR(ISBLANK(B21),ISBLANK('自学 （6级）'!B21)),"", IF(B21='自学 （6级）'!B21,"",'自学 （6级）'!B21)) | G21: 熬
A22: ='自学 （6级）'!D22 -> Forthright | C22: =IF(OR(ISBLANK(B22),'自学 （6级）'!B22=""),"UNANSWERED", IF('自学 （6级）'!B22=B22,"TRUE","FALSE")) -> UNANSWERED | D22: =IF(OR(ISBLANK(B22),ISBLANK('自学 （6级）'!B22)),"", IF(B22='自学 （6级）'!B22,"",'自学 （6级）'!B22)) | G22: 酝酿
A23: ='自学 （6级）'!D23 -> On good term with | C23: =IF(OR(ISBLANK(B23),'自学 （6级）'!B23=""),"UNANSWERED", IF('自学 （6级）'!B23=B23,"TRUE","FALSE")) -> UNANSWERED | D23: =IF(OR(ISBLANK(B23),ISBLANK('自学 （6级）'!B23)),"", IF(B23='自学 （6级）'!B23,"",'自学 （6级）'!B23)) | G23: 流露
A24: ='自学 （6级）'!D24 -> Harmonious | C24: =IF(OR(ISBLANK(B24),'自学 （6级）'!B24=""),"UNANSWERED", IF('自学 （6级）'!B24=B24,"TRUE","FALSE")) -> UNANSWERED | D24: =IF(OR(ISBLANK(B24),ISBLANK('自学 （6级）'!B24)),"", IF(B24='自学 （6级）'!B24,"",'自学 （6级）'!B24)) | G24: 操劳
A25: ='自学 （6级）'!D25 -> To chime with | C25: =IF(OR(ISBLANK(B25),'自学 （6级）'!B25=""),"UNANSWERED", IF('自学 （6级）'!B25=B25,"TRUE","FALSE")) -> UNANSWERED | D25: =IF(OR(ISBLANK(B25),ISBLANK('自学 （6级）'!B25)),"", IF(B25='自学 （6级）'!B25,"",'自学 （6级）'!B25)) | G25: 惦记
A26: ='自学 （6级）'!D26 -> ignore | C26: =IF(OR(ISBLANK(B26),'自学 （6级）'!B26=""),"UNANSWERED", IF('自学 （6级）'!B26=B26,"TRUE","FALSE")) -> UNANSWERED | D26: =IF(OR(ISBLANK(B26),ISBLANK('自学 （6级）'!B26)),"", IF(B26='自学 （6级）'!B26,"",'自学 （6级）'!B26)) | G26: 设置
A27: ='自学 （6级）'!D27 -> instant | C27: =IF(OR(ISBLANK(B27),'自学 （6级）'!B27=""),"UNANSWERED", IF('自学 （6级）'!B27=B27,"TRUE","FALSE")) -> UNANSWERED | D27: =IF(OR(ISBLANK(B27),ISBLANK('自学 （6级）'!B27)),"", IF(B27='自学 （6级）'!B27,"",'自学 （6级）'!B27)) | G27: 机构
A28: ='自学 （6级）'!D28 -> industrious, diligent | C28: =IF(OR(ISBLANK(B28),'自学 （6级）'!B28=""),"UNANSWERED", IF('自学 （6级）'!B28=B28,"TRUE","FALSE")) -> UNANSWERED | D28: =IF(OR(ISBLANK(B28),ISBLANK('自学 （6级）'!B28)),"", IF(B28='自学 （6级）'!B28,"",'自学 （6级）'!B28)) | G28: 反感
A29: ='自学 （6级）'!D29 -> delicious food | C29: =IF(OR(ISBLANK(B29),'自学 （6级）'!B29=""),"UNANSWERED", IF('自学 （6级）'!B29=B29,"TRUE","FALSE")) -> UNANSWERED | D29: =IF(OR(ISBLANK(B29),ISBLANK('自学 （6级）'!B29)),"", IF(B29='自学 （6级）'!B29,"",'自学 （6级）'!B29)) | G29: 不料
A30: ='自学 （6级）'!D30 -> to be eager | C30: =IF(OR(ISBLANK(B30),'自学 （6级）'!B30=""),"UNANSWERED", IF('自学 （6级）'!B30=B30,"TRUE","FALSE")) -> UNANSWERED | D30: =IF(OR(ISBLANK(B30),ISBLANK('自学 （6级）'!B30)),"", IF(B30='自学 （6级）'!B30,"",'自学 （6级）'!B30)) | G30: 未免
A31: ='自学 （6级）'!D31 -> to shout | C31: =IF(OR(ISBLANK(B31),'自学 （6级）'!B31=""),"UNANSWERED", IF('自学 （6级）'!B31=B31,"TRUE","FALSE")) -> UNANSWERED | D31: =IF(OR(ISBLANK(B31),ISBLANK('自学 （6级）'!B31)),"", IF(B31='自学 （6级）'!B31,"",'自学 （6级）'!B31)) | G31: 悲惨
... A45: ='自学 （6级）'!D45 -> to conceal | C45: =IF(OR(ISBLANK(B45),'自学 （6级）'!B45=""),"UNANSWERED", IF('自学 （6级）'!B45=B45,"TRUE","FALSE")) -> UNANSWERED | D45: =IF(OR(ISBLANK(B45),ISBLANK('自学 （6级）'!B45)),"", IF(B45='自学 （6级）'!B45,"",'自学 （6级）'!B45)) | G45: 意志
A46: ='自学 （6级）'!D46 -> to blame, to complain | C46: =IF(OR(ISBLANK(B46),'自学 （6级）'!B46=""),"UNANSWERED", IF('自学 （6级）'!B46=B46,"TRUE","FALSE")) -> UNANSWERED | D46: =IF(OR(ISBLANK(B46),ISBLANK('自学 （6级）'!B46)),"", IF(B46='自学 （6级）'!B46,"",'自学 （6级）'!B46))
A47: ='自学 （6级）'!D47 -> unusual, abnormal | C47: =IF(OR(ISBLANK(B47),'自学 （6级）'!B47=""),"UNANSWERED", IF('自学 （6级）'!B47=B47,"TRUE","FALSE")) -> UNANSWERED | D47: =IF(OR(ISBLANK(B47),ISBLANK('自学 （6级）'!B47)),"", IF(B47='自学 （6级）'!B47,"",'自学 （6级）'!B47))
A48: ='自学 （6级）'!D48 -> to endure | C48: =IF(OR(ISBLANK(B48),'自学 （6级）'!B48=""),"UNANSWERED", IF('自学 （6级）'!B48=B48,"TRUE","FALSE")) -> UNANSWERED | D48: =IF(OR(ISBLANK(B48),ISBLANK('自学 （6级）'!B48)),"", IF(B48='自学 （6级）'!B48,"",'自学 （6级）'!B48))
A49: ='自学 （6级）'!D49 -> to ferment | C49: =IF(OR(ISBLANK(B49),'自学 （6级）'!B49=""),"UNANSWERED", IF('自学 （6级）'!B49=B49,"TRUE","FALSE")) -> UNANSWERED | D49: =IF(OR(ISBLANK(B49),ISBLANK('自学 （6级）'!B49)),"", IF(B49='自学 （6级）'!B49,"",'自学 （6级）'!B49))
A50: ='自学 （6级）'!D50 -> Face to face | C50: =IF(OR(ISBLANK(B50),'自学 （6级）'!B50=""),"UNANSWERED", IF('自学 （6级）'!B50=B50,"TRUE","FALSE")) -> UNANSWERED | D50: =IF(OR(ISBLANK(B50),ISBLANK('自学 （6级）'!B50)),"", IF(B50='自学 （6级）'!B50,"",'自学 （6级）'!B50))
A51: ='自学 （6级）'!D51 -> Hesitate | C51: =IF(OR(ISBLANK(B51),'自学 （6级）'!B51=""),"UNANSWERED", IF('自学 （6级）'!B51=B51,"TRUE","FALSE")) -> UNANSWERED | D51: =IF(OR(ISBLANK(B51),ISBLANK('自学 （6级）'!B51)),"", IF(B51='自学 （6级）'!B51,"",'自学 （6级）'!B51))
A52: ='自学 （6级）'!D52 -> To look up and down | C52: =IF(OR(ISBLANK(B52),'自学 （6级）'!B52=""),"UNANSWERED", IF('自学 （6级）'!B52=B52,"TRUE","FALSE")) -> UNANSWERED | D52: =IF(OR(ISBLANK(B52),ISBLANK('自学 （6级）'!B52)),"", IF(B52='自学 （6级）'!B52,"",'自学 （6级）'!B52))
A53: ='自学 （6级）'!D53 -> To rub ones hand | C53: =IF(OR(ISBLANK(B53),'自学 （6级）'!B53=""),"UNANSWERED", IF('自学 （6级）'!B53=B53,"TRUE","FALSE")) -> UNANSWERED | D53: =IF(OR(ISBLANK(B53),ISBLANK('自学 （6级）'!B53)),"", IF(B53='自学 （6级）'!B53,"",'自学 （6级）'!B53))
A54: ='自学 （6级）'!D54 -> To reveal unintentionally | C54: =IF(OR(ISBLANK(B54),'自学 （6级）'!B54=""),"UNANSWERED", IF('自学 （6级）'!B54=B54,"TRUE","FALSE")) -> UNANSWERED | D54: =IF(OR(ISBLANK(B54),ISBLANK('自学 （6级）'!B54)),"", IF(B54='自学 （6级）'!B54,"",'自学 （6级）'!B54))
A55: ='自学 （6级）'!D55 -> Too, Exceedingly | C55: =IF(OR(ISBLANK(B55),'自学 （6级）'!B55=""),"UNANSWERED", IF('自学 （6级）'!B55=B55,"TRUE","FALSE")) -> UNANSWERED | D55: =IF(OR(ISBLANK(B55),ISBLANK('自学 （6级）'!B55)),"", IF(B55='自学 （6级）'!B55,"",'自学 （6级）'!B55))
A56: ='自学 （6级）'!D56 -> gentle, refine | C56: =IF(OR(ISBLANK(B56),'自学 （6级）'!B56=""),"UNANSWERED", IF('自学 （6级）'!B56=B56,"TRUE","FALSE")) -> UNANSWERED | D56: =IF(OR(ISBLANK(B56),ISBLANK('自学 （6级）'!B56)),"", IF(B56='自学 （6级）'!B56,"",'自学 （6级）'!B56))
A57: ='自学 （6级）'!D57 -> Diligent | C57: =IF(OR(ISBLANK(B57),'自学 （6级）'!B57=""),"UNANSWERED", IF('自学 （6级）'!B57=B57,"TRUE","FALSE")) -> UNANSWERED | D57: =IF(OR(ISBLANK(B57),ISBLANK('自学 （6级）'!B57)),"", IF(B57='自学 （6级）'!B57,"",'自学 （6级）'!B57))
... A70: ='自学 （6级）'!D70 -> To carry out, to implement | C70: =IF(OR(ISBLANK(B70),'自学 （6级）'!B70=""),"UNANSWERED", IF('自学 （6级）'!B70=B70,"TRUE","FALSE")) -> UNANSWERED | D70: =IF(OR(ISBLANK(B70),ISBLANK('自学 （6级）'!B70)),"", IF(B70='自学 （6级）'!B70,"",'自学 （6级）'!B70))
A71: ='自学 （6级）'!D71 -> To set up, Established | C71: =IF(OR(ISBLANK(B71),'自学 （6级）'!B71=""),"UNANSWERED", IF('自学 （6级）'!B71=B71,"TRUE","FALSE")) -> UNANSWERED | D71: =IF(OR(ISBLANK(B71),ISBLANK('自学 （6级）'!B71)),"", IF(B71='自学 （6级）'!B71,"",'自学 （6级）'!B71)) | F71: =($F$1/312) -> 0.50641026
A72: ='自学 （6级）'!D72 -> Organization, institution | C72: =IF(OR(ISBLANK(B72),'自学 （6级）'!B72=""),"UNANSWERED", IF('自学 （6级）'!B72=B72,"TRUE","FALSE")) -> UNANSWERED | D72: =IF(OR(ISBLANK(B72),ISBLANK('自学 （6级）'!B72)),"", IF(B72='自学 （6级）'!B72,"",'自学 （6级）'!B72))
A73: ='自学 （6级）'!D73 -> digusted | C73: =IF(OR(ISBLANK(B73),'自学 （6级）'!B73=""),"UNANSWERED", IF('自学 （6级）'!B73=B73,"TRUE","FALSE")) -> UNANSWERED | D73: =IF(OR(ISBLANK(B73),ISBLANK('自学 （6级）'!B73)),"", IF(B73='自学 （6级）'!B73,"",'自学 （6级）'!B73))
A74: ='自学 （6级）'!D74 -> unexpectly, to ones surprise | C74: =IF(OR(ISBLANK(B74),'自学 （6级）'!B74=""),"UNANSWERED", IF('自学 （6级）'!B74=B74,"TRUE","FALSE")) -> UNANSWERED | D74: =IF(OR(ISBLANK(B74),ISBLANK('自学 （6级）'!B74)),"", IF(B74='自学 （6级）'!B74,"",'自学 （6级）'!B74))
A75: ='自学 （6级）'!D75 -> rather, a bit too | C75: =IF(OR(ISBLANK(B75),'自学 （6级）'!B75=""),"UNANSWERED", IF('自学 （6级）'!B75=B75,"TRUE","FALSE")) -> UNANSWERED | D75: =IF(OR(ISBLANK(B75),ISBLANK('自学 （6级）'!B75)),"", IF(B75='自学 （6级）'!B75,"",'自学 （6级）'!B75))
A76: ='自学 （6级）'!D76 -> hateful, detestable | C76: =IF(OR(ISBLANK(B76),'自学 （6级）'!B76=""),"UNANSWERED", IF('自学 （6级）'!B76=B76,"TRUE","FALSE")) -> UNANSWERED | D76: =IF(OR(ISBLANK(B76),ISBLANK('自学 （6级）'!B76)),"", IF(B76='自学 （6级）'!B76,"",'自学 （6级）'!B76))
A77: ='自学 （6级）'!D77 -> to despise, to look down upon | C77: =IF(OR(ISBLANK(B77),'自学 （6级）'!B77=""),"UNANSWERED", IF('自学 （6级）'!B77=B77,"TRUE","FALSE")) -> UNANSWERED | D77: =IF(OR(ISBLANK(B77),ISBLANK('自学 （6级）'!B77)),"", IF(B77='自学 （6级）'!B77,"",'自学 （6级）'!B77))
A78: ='自学 （6级）'!D78 -> to breathe deeply, to gasp, to pant | C78: =IF(OR(ISBLANK(B78),'自学 （6级）'!B78=""),"UNANSWERED", IF('自学 （6级）'!B78=B78,"TRUE","FALSE")) -> UNANSWERED | D78: =IF(OR(ISBLANK(B78),ISBLANK('自学 （6级）'!B78)),"", IF(B78='自学 （6级）'!B78,"",'自学 （6级）'!B78))
A79: ='自学 （6级）'!D79 -> fierce, violent | C79: =IF(OR(ISBLANK(B79),'自学 （6级）'!B79=""),"UNANSWERED", IF('自学 （6级）'!B79=B79,"TRUE","FALSE")) -> UNANSWERED | D79: =IF(OR(ISBLANK(B79),ISBLANK('自学 （6级）'!B79)),"", IF(B79='自学 （6级）'!B79,"",'自学 （6级）'!B79))
A80: ='自学 （6级）'!D80 -> to hunt, to go hunting | C80: =IF(OR(ISBLANK(B80),'自学 （6级）'!B80=""),"UNANSWERED", IF('自学 （6级）'!B80=B80,"TRUE","FALSE")) -> UNANSWERED | D80: =IF(OR(ISBLANK(B80),ISBLANK('自学 （6级）'!B80)),"", IF(B80='自学 （6级）'!B80,"",'自学 （6级）'!B80))
A81: ='自学 （6级）'!D81 -> in the least, without | C81: =IF(OR(ISBLANK(B81),'自学 （6级）'!B81=""),"UNANSWERED", IF('自学 （6级）'!B81=B81,"TRUE","FALSE")) -> UNANSWERED | D81: =IF(OR(ISBLANK(B81),ISBLANK('自学 （6级）'!B81)),"", IF(B81='自学 （6级）'!B81,"",'自学 （6级）'!B81))
A82: ='自学 （6级）'!D82 -> disadvantage, draw back | C82: =IF(OR(ISBLANK(B82),'自学 （6级）'!B82=""),"UNANSWERED", IF('自学 （6级）'!B82=B82,"TRUE","FALSE")) -> UNANSWERED | D82: =IF(OR(ISBLANK(B82),ISBLANK('自学 （6级）'!B82)),"", IF(B82='自学 （6级）'!B82,"",'自学 （6级）'!B82))
A83: ='自学 （6级）'!D83 -> nothing but, no more than | C83: =IF(OR(ISBLANK(B83),'自学 （6级）'!B83=""),"UNANSWERED", IF('自学 （6级）'!B83=B83,"TRUE","FALSE")) -> UNANSWERED | D83: =IF(OR(ISBLANK(B83),ISBLANK('自学 （6级）'!B83)),"", IF(B83='自学 （6级）'!B83,"",'自学 （6级）'!B83))
... A90: ='自学 （6级）'!D90 -> to stare at, to fix one's eyes | C90: =IF(OR(ISBLANK(B90),'自学 （6级）'!B90=""),"UNANSWERED", IF('自学 （6级）'!B90=B90,"TRUE","FALSE")) -> UNANSWERED | D90: =IF(OR(ISBLANK(B90),ISBLANK('自学 （6级）'!B90)),"", IF(B90='自学 （6级）'!B90,"",'自学 （6级）'!B90))
A91: ='自学 （6级）'!D91 -> to forgive, to pardon | B91: 体谅 | C91: =IF(OR(ISBLANK(B91),'自学 （6级）'!B91=""),"UNANSWERED", IF('自学 （6级）'!B91=B91,"TRUE","FALSE")) -> FALSE | D91: =IF(OR(ISBLANK(B91),ISBLANK('自学 （6级）'!B91)),"", IF(B91='自学 （6级）'!B91,"",'自学 （6级）'!B91)) -> 饶恕
A92: ='自学 （6级）'!D92 -> to play, to behave | B92: 耍 | C92: =IF(OR(ISBLANK(B92),'自学 （6级）'!B92=""),"UNANSWERED", IF('自学 （6级）'!B92=B92,"TRUE","FALSE")) -> TRUE | D92: =IF(OR(ISBLANK(B92),ISBLANK('自学 （6级）'!B92)),"", IF(B92='自学 （6级）'!B92,"",'自学 （6级）'!B92))
A93: ='自学 （6级）'!D93 -> to flee, to scurry | B93: 窜 | C93: =IF(OR(ISBLANK(B93),'自学 （6级）'!B93=""),"UNANSWERED", IF('自学 （6级）'!B93=B93,"TRUE","FALSE")) -> TRUE | D93: =IF(OR(ISBLANK(B93),ISBLANK('自学 （6级）'!B93)),"", IF(B93='自学 （6级）'!B93,"",'自学 （6级）'!B93))
A94: ='自学 （6级）'!D94 -> use, to consme | B94: 耗费 | C94: =IF(OR(ISBLANK(B94),'自学 （6级）'!B94=""),"UNANSWERED", IF('自学 （6级）'!B94=B94,"TRUE","FALSE")) -> TRUE | D94: =IF(OR(ISBLANK(B94),ISBLANK('自学 （6级）'!B94)),"", IF(B94='自学 （6级）'!B94,"",'自学 （6级）'!B94))
A95: ='自学 （6级）'!D95 -> to collapse, to fall apart | B95: 崩溃 | C95: =IF(OR(ISBLANK(B95),'自学 （6级）'!B95=""),"UNANSWERED", IF('自学 （6级）'!B95=B95,"TRUE","FALSE")) -> TRUE | D95: =IF(OR(ISBLANK(B95),ISBLANK('自学 （6级）'!B95)),"", IF(B95='自学 （6级）'!B95,"",'自学 （6级）'!B95))
A96: ='自学 （6级）'!D96 -> admittely, it is true | B96: 固然 | C96: =IF(OR(ISBLANK(B96),'自学 （6级）'!B96=""),"UNANSWERED", IF('自学 （6级）'!B96=B96,"TRUE","FALSE")) -> TRUE | D96: =IF(OR(ISBLANK(B96),ISBLANK('自学 （6级）'!B96)),"", IF(B96='自学 （6级）'!B96,"",'自学 （6级）'!B96)) | E96: 固有 | F96: 固然
A97: ='自学 （6级）'!D97 -> to manage with effort, to do with difficulty | B97: 勉强 | C97: =IF(OR(ISBLANK(B97),'自学 （6级）'!B97=""),"UNANSWERED", IF('自学 （6级）'!B97=B97,"TRUE","FALSE")) -> TRUE | D97: =IF(OR(ISBLANK(B97),ISBLANK('自学 （6级）'!B97)),"", IF(B97='自学 （6级）'!B97,"",'自学 （6级）'!B97))
A98: ='自学 （6级）'!D98 -> privacy | B98: 隐私 | C98: =IF(OR(ISBLANK(B98),'自学 （6级）'!B98=""),"UNANSWERED", IF('自学 （6级）'!B98=B98,"TRUE","FALSE")) -> TRUE | D98: =IF(OR(ISBLANK(B98),ISBLANK('自学 （6级）'!B98)),"", IF(B98='自学 （6级）'!B98,"",'自学 （6级）'!B98))
A99: ='自学 （6级）'!D99 -> if suppoosing | B99: 倘若 | C99: =IF(OR(ISBLANK(B99),'自学 （6级）'!B99=""),"UNANSWERED", IF('自学 （6级）'!B99=B99,"TRUE","FALSE")) -> TRUE | D99: =IF(OR(ISBLANK(B99),ISBLANK('自学 （6级）'!B99)),"", IF(B99='自学 （6级）'!B99,"",'自学 （6级）'!B99))
A100: ='自学 （6级）'!D100 -> by chance | B100: 不料 | C100: =IF(OR(ISBLANK(B100),'自学 （6级）'!B100=""),"UNANSWERED", IF('自学 （6级）'!B100=B100,"TRUE","FALSE")) -> FALSE | D100: =IF(OR(ISBLANK(B100),ISBLANK('自学 （6级）'!B100)),"", IF(B100='自学 （6级）'!B100,"",'自学 （6级）'!B100)) -> 恰巧
A101: ='自学 （6级）'!D101 -> hateful, tragic | B101: 悲惨 | C101: =IF(OR(ISBLANK(B101),'自学 （6级）'!B101=""),"UNANSWERED", IF('自学 （6级）'!B101=B101,"TRUE","FALSE")) -> FALSE | D101: =IF(OR(ISBLANK(B101),ISBLANK('自学 （6级）'!B101)),"", IF(B101='自学 （6级）'!B101,"",'自学 （6级）'!B101)) -> 蔑视
A102: ='自学 （6级）'!D102 -> to force | B102: 强迫 | C102: =IF(OR(ISBLANK(B102),'自学 （6级）'!B102=""),"UNANSWERED", IF('自学 （6级）'!B102=B102,"TRUE","FALSE")) -> TRUE | D102: =IF(OR(ISBLANK(B102),ISBLANK('自学 （6级）'!B102)),"", IF(B102='自学 （6级）'!B102,"",'自学 （6级）'!B102))
A103: ='自学 （6级）'!D103 -> setting sun | B103: 夕阳 | C103: =IF(OR(ISBLANK(B103),'自学 （6级）'!B103=""),"UNANSWERED", IF('自学 （6级）'!B103=B103,"TRUE","FALSE")) -> TRUE | D103: =IF(OR(ISBLANK(B103),ISBLANK('自学 （6级）'!B103)),"", IF(B103='自学 （6级）'!B103,"",'自学 （6级）'!B103))
A104: ='自学 （6级）'!D104 -> to get rid of, to break away | B104: 摆脱 | C104: =IF(OR(ISBLANK(B104),'自学 （6级）'!B104=""),"UNANSWERED", IF('自学 （6级）'!B104=B104,"TRUE","FALSE")) -> TRUE | D104: =IF(OR(ISBLANK(B104),ISBLANK('自学 （6级）'!B104)),"", IF(B104='自学 （6级）'!B104,"",'自学 （6级）'!B104))
A105: ='自学 （6级）'!D105 -> careless, rash | B105: 草率 | C105: =IF(OR(ISBLANK(B105),'自学 （6级）'!B105=""),"UNANSWERED", IF('自学 （6级）'!B105=B105,"TRUE","FALSE")) -> TRUE | D105: =IF(OR(ISBLANK(B105),ISBLANK('自学 （6级）'!B105)),"", IF(B105='自学 （6级）'!B105,"",'自学 （6级）'!B105))
A106: ='自学 （6级）'!D106 -> to dedicate oneself to work | B106: 敬业 | C106: =IF(OR(ISBLANK(B106),'自学 （6级）'!B106=""),"UNANSWERED", IF('自学 （6级）'!B106=B106,"TRUE","FALSE")) -> TRUE | D106: =IF(OR(ISBLANK(B106),ISBLANK('自学 （6级）'!B106)),"", IF(B106='自学 （6级）'!B106,"",'自学 （6级）'!B106))
A107: ='自学 （6级）'!D107 -> to teach, to impart | B107: 教授 | C107: =IF(OR(ISBLANK(B107),'自学 （6级）'!B107=""),"UNANSWERED", IF('自学 （6级）'!B107=B107,"TRUE","FALSE")) -> FALSE | D107: =IF(OR(ISBLANK(B107),ISBLANK('自学 （6级）'!B107)),"", IF(B107='自学 （6级）'!B107,"",'自学 （6级）'!B107)) -> 传授
A108: ='自学 （6级）'!D108 -> to boast, to brag | B108: 吹牛 | C108: =IF(OR(ISBLANK(B108),'自学 （6级）'!B108=""),"UNANSWERED", IF('自学 （6级）'!B108=B108,"TRUE","FALSE")) -> TRUE | D108: =IF(OR(ISBLANK(B108),ISBLANK('自学 （6级）'!B108)),"", IF(B108='自学 （6级）'!B108,"",'自学 （6级）'!B108))
... A143: ='自学 （6级）'!D143 -> consequently, as a result | B143: 以致 | C143: =IF(OR(ISBLANK(B143),'自学 （6级）'!B143=""),"UNANSWERED", IF('自学 （6级）'!B143=B143,"TRUE","FALSE")) -> TRUE | D143: =IF(OR(ISBLANK(B143),ISBLANK('自学 （6级）'!B143)),"", IF(B143='自学 （6级）'!B143,"",'自学 （6级）'!B143))
A144: ='自学 （6级）'!D144 -> to be saturated, to be filled | B144: 饱和 | C144: =IF(OR(ISBLANK(B144),'自学 （6级）'!B144=""),"UNANSWERED", IF('自学 （6级）'!B144=B144,"TRUE","FALSE")) -> TRUE | D144: =IF(OR(ISBLANK(B144),ISBLANK('自学 （6级）'!B144)),"", IF(B144='自学 （6级）'!B144,"",'自学 （6级）'!B144)) | F144: =($F$1/312) -> 0.50641026
A145: ='自学 （6级）'!D145 -> as soon as possible, before it is too late | B145: 及早 | C145: =IF(OR(ISBLANK(B145),'自学 （6级）'!B145=""),"UNANSWERED", IF('自学 （6级）'!B145=B145,"TRUE","FALSE")) -> TRUE | D145: =IF(OR(ISBLANK(B145),ISBLANK('自学 （6级）'!B145)),"", IF(B145='自学 （6级）'!B145,"",'自学 （6级）'!B145))
A146: ='自学 （6级）'!D146 -> opportunity, luck | B146: 机遇 | C146: =IF(OR(ISBLANK(B146),'自学 （6级）'!B146=""),"UNANSWERED", IF('自学 （6级）'!B146=B146,"TRUE","FALSE")) -> TRUE | D146: =IF(OR(ISBLANK(B146),ISBLANK('自学 （6级）'!B146)),"", IF(B146='自学 （6级）'!B146,"",'自学 （6级）'!B146))
A147: ='自学 （6级）'!D147 -> to be immunue | B147: 免疫 | C147: =IF(OR(ISBLANK(B147),'自学 （6级）'!B147=""),"UNANSWERED", IF('自学 （6级）'!B147=B147,"TRUE","FALSE")) -> TRUE | D147: =IF(OR(ISBLANK(B147),ISBLANK('自学 （6级）'!B147)),"", IF(B147='自学 （6级）'!B147,"",'自学 （6级）'!B147))
A148: ='自学 （6级）'!D148 -> to make a strategic decision | B148: 决策 | C148: =IF(OR(ISBLANK(B148),'自学 （6级）'!B148=""),"UNANSWERED", IF('自学 （6级）'!B148=B148,"TRUE","FALSE")) -> TRUE | D148: =IF(OR(ISBLANK(B148),ISBLANK('自学 （6级）'!B148)),"", IF(B148='自学 （6级）'!B148,"",'自学 （6级）'!B148))
A149: ='自学 （6级）'!D149 -> Soil | B149: 土壤 | C149: =IF(OR(ISBLANK(B149),'自学 （6级）'!B149=""),"UNANSWERED", IF('自学 （6级）'!B149=B149,"TRUE","FALSE")) -> TRUE | D149: =IF(OR(ISBLANK(B149),ISBLANK('自学 （6级）'!B149)),"", IF(B149='自学 （6级）'!B149,"",'自学 （6级）'!B149))
A150: ='自学 （6级）'!D150 -> Steep, Precipious | B150: 陡峭 | C150: =IF(OR(ISBLANK(B150),'自学 （6级）'!B150=""),"UNANSWERED", IF('自学 （6级）'!B150=B150,"TRUE","FALSE")) -> TRUE | D150: =IF(OR(ISBLANK(B150),ISBLANK('自学 （6级）'!B150)),"", IF(B150='自学 （6级）'!B150,"",'自学 （6级）'!B150))
A151: ='自学 （6级）'!D151 -> Luxuriant, exuberant | B151: 不知道 | C151: =IF(OR(ISBLANK(B151),'自学 （6级）'!B151=""),"UNANSWERED", IF('自学 （6级）'!B151=B151,"TRUE","FALSE")) -> FALSE | D151: =IF(OR(ISBLANK(B151),ISBLANK('自学 （6级）'!B151)),"", IF(B151='自学 （6级）'!B151,"",'自学 （6级）'!B151)) -> 茂盛
A152: ='自学 （6级）'!D152 -> to hang, to suspend | B152: 坠 | C152: =IF(OR(ISBLANK(B152),'自学 （6级）'!B152=""),"UNANSWERED", IF('自学 （6级）'!B152=B152,"TRUE","FALSE")) -> FALSE | D152: =IF(OR(ISBLANK(B152),ISBLANK('自学 （6级）'!B152)),"", IF(B152='自学 （6级）'!B152,"",'自学 （6级）'!B152)) -> 悬挂
A153: ='自学 （6级）'!D153 -> to bear, to shoulder | B153: 辜负 | C153: =IF(OR(ISBLANK(B153),'自学 （6级）'!B153=""),"UNANSWERED", IF('自学 （6级）'!B153=B153,"TRUE","FALSE")) -> FALSE | D153: =IF(OR(ISBLANK(B153),ISBLANK('自学 （6级）'!B153)),"", IF(B153='自学 （6级）'!B153,"",'自学 （6级）'!B153)) -> 负担
A154: ='自学 （6级）'!D154 -> to fall, to drop | B154: 坠 | C154: =IF(OR(ISBLANK(B154),'自学 （6级）'!B154=""),"UNANSWERED", IF('自学 （6级）'!B154=B154,"TRUE","FALSE")) -> TRUE | D154: =IF(OR(ISBLANK(B154),ISBLANK('自学 （6级）'!B154)),"", IF(B154='自学 （6级）'!B154,"",'自学 （6级）'!B154))
A155: ='自学 （6级）'!D155 -> to hang, to suspend, to dangle | B155: 吊 | C155: =IF(OR(ISBLANK(B155),'自学 （6级）'!B155=""),"UNANSWERED", IF('自学 （6级）'!B155=B155,"TRUE","FALSE")) -> TRUE | D155: =IF(OR(ISBLANK(B155),ISBLANK('自学 （6级）'!B155)),"", IF(B155='自学 （6级）'!B155,"",'自学 （6级）'!B155))
A156: ='自学 （6级）'!D156 -> to decorate, to adorn | B156: 点 | C156: =IF(OR(ISBLANK(B156),'自学 （6级）'!B156=""),"UNANSWERED", IF('自学 （6级）'!B156=B156,"TRUE","FALSE")) -> FALSE | D156: =IF(OR(ISBLANK(B156),ISBLANK('自学 （6级）'!B156)),"", IF(B156='自学 （6级）'!B156,"",'自学 （6级）'!B156)) -> 点缀
... A183: ='自学 （6级）'!D183 -> to twinkle, to flicker, to glitter | B183: 闪烁 | C183: =IF(OR(ISBLANK(B183),'自学 （6级）'!B183=""),"UNANSWERED", IF('自学 （6级）'!B183=B183,"TRUE","FALSE")) -> TRUE | D183: =IF(OR(ISBLANK(B183),ISBLANK('自学 （6级）'!B183)),"", IF(B183='自学 （6级）'!B183,"",'自学 （6级）'!B183))
A184: ='自学 （6级）'!D184 -> vision, eyesight | B184: 视力 | C184: =IF(OR(ISBLANK(B184),'自学 （6级）'!B184=""),"UNANSWERED", IF('自学 （6级）'!B184=B184,"TRUE","FALSE")) -> FALSE | D184: =IF(OR(ISBLANK(B184),ISBLANK('自学 （6级）'!B184)),"", IF(B184='自学 （6级）'!B184,"",'自学 （6级）'!B184)) -> 实力 | F184: 对
A185: ='自学 （6级）'!D185 -> elegant, refined, polished | B185: 文雅 | C185: =IF(OR(ISBLANK(B185),'自学 （6级）'!B185=""),"UNANSWERED", IF('自学 （6级）'!B185=B185,"TRUE","FALSE")) -> TRUE | D185: =IF(OR(ISBLANK(B185),ISBLANK('自学 （6级）'!B185)),"", IF(B185='自学 （6级）'!B185,"",'自学 （6级）'!B185))
A186: ='自学 （6级）'!D186 -> metabolism | B186: 新陈代谢（代谢） | C186: =IF(OR(ISBLANK(B186),'自学 （6级）'!B186=""),"UNANSWERED", IF('自学 （6级）'!B186=B186,"TRUE","FALSE")) -> FALSE | D186: =IF(OR(ISBLANK(B186),ISBLANK('自学 （6级）'!B186)),"", IF(B186='自学 （6级）'!B186,"",'自学 （6级）'!B186)) -> 新陈代谢 （代谢）
A187: ='自学 （6级）'!D187 -> ranking, place in a competition | B187: 名次 | C187: =IF(OR(ISBLANK(B187),'自学 （6级）'!B187=""),"UNANSWERED", IF('自学 （6级）'!B187=B187,"TRUE","FALSE")) -> TRUE | D187: =IF(OR(ISBLANK(B187),ISBLANK('自学 （6级）'!B187)),"", IF(B187='自学 （6级）'!B187,"",'自学 （6级）'!B187))
A188: ='自学 （6级）'!D188 -> to infer, to deduce | B188: 正论 | C188: =IF(OR(ISBLANK(B188),'自学 （6级）'!B188=""),"UNANSWERED", IF('自学 （6级）'!B188=B188,"TRUE","FALSE")) -> FALSE | D188: =IF(OR(ISBLANK(B188),ISBLANK('自学 （6级）'!B188)),"", IF(B188='自学 （6级）'!B188,"",'自学 （6级）'!B188)) -> 推论
A189: ='自学 （6级）'!D189 -> practical, affordable, substantial | B189: 实惠 | C189: =IF(OR(ISBLANK(B189),'自学 （6级）'!B189=""),"UNANSWERED", IF('自学 （6级）'!B189=B189,"TRUE","FALSE")) -> TRUE | D189: =IF(OR(ISBLANK(B189),ISBLANK('自学 （6级）'!B189)),"", IF(B189='自学 （6级）'!B189,"",'自学 （6级）'!B189))
A190: ='自学 （6级）'!D190 -> tiny, insgnificant | B190: 渺小 | C190: =IF(OR(ISBLANK(B190),'自学 （6级）'!B190=""),"UNANSWERED", IF('自学 （6级）'!B190=B190,"TRUE","FALSE")) -> TRUE | D190: =IF(OR(ISBLANK(B190),ISBLANK('自学 （6级）'!B190)),"", IF(B190='自学 （6级）'!B190,"",'自学 （6级）'!B190))
A191: ='自学 （6级）'!D191 -> anxious, agitated | B191: 焦急 | C191: =IF(OR(ISBLANK(B191),'自学 （6级）'!B191=""),"UNANSWERED", IF('自学 （6级）'!B191=B191,"TRUE","FALSE")) -> TRUE | D191: =IF(OR(ISBLANK(B191),ISBLANK('自学 （6级）'!B191)),"", IF(B191='自学 （6级）'!B191,"",'自学 （6级）'!B191))
...
